requests_mock_flask/__init__.py
requests_mock_flask/py.typed
requests_mock_flask-2025.1.13.dist-info/LICENSE
requests_mock_flask-2025.1.13.dist-info/METADATA
requests_mock_flask-2025.1.13.dist-info/WHEEL
requests_mock_flask-2025.1.13.dist-info/top_level.txt
requests_mock_flask-2025.1.13.dist-info/RECORD
