Metadata-Version: 2.2
Name: requests-mock-flask
Version: 2025.1.13
Summary: Helpers to use requests_mock and responses with a Flask test client.
Author-email: Adam Dangoor <adamdangoor@gmail.com>
License: MIT License
Project-URL: Source, https://github.com/adamtheturtle/requests-mock-flask
Keywords: flask,mock,requests
Classifier: Development Status :: 5 - Production/Stable
Classifier: Environment :: Web Environment
Classifier: Framework :: Pytest
Classifier: License :: OSI Approved :: MIT License
Classifier: Operating System :: Microsoft :: Windows
Classifier: Operating System :: POSIX
Classifier: Programming Language :: Python :: 3 :: Only
Classifier: Programming Language :: Python :: 3.12
Classifier: Programming Language :: Python :: 3.13
Requires-Python: >=3.12
License-File: LICENSE
Requires-Dist: httpretty>=1.1.4
Requires-Dist: requests-mock>=1.12.1
Requires-Dist: responses!=0.25.5,>=0.25.3
Requires-Dist: werkzeug>=2.3
Provides-Extra: dev
Requires-Dist: actionlint-py==1.7.6.22; extra == "dev"
Requires-Dist: beartype==0.19.0; extra == "dev"
Requires-Dist: check-manifest==0.50; extra == "dev"
Requires-Dist: deptry==0.22.0; extra == "dev"
Requires-Dist: doc8==1.1.2; extra == "dev"
Requires-Dist: doccmd==2025.1.11; extra == "dev"
Requires-Dist: docformatter==1.7.5; extra == "dev"
Requires-Dist: flask==3.1.0; extra == "dev"
Requires-Dist: furo==2024.8.6; extra == "dev"
Requires-Dist: interrogate==1.7.0; extra == "dev"
Requires-Dist: mypy[faster-cache]==1.14.1; extra == "dev"
Requires-Dist: mypy-strict-kwargs==2024.12.25; extra == "dev"
Requires-Dist: pre-commit==4.0.1; extra == "dev"
Requires-Dist: pylint==3.3.3; extra == "dev"
Requires-Dist: pylint-per-file-ignores==1.3.2; extra == "dev"
Requires-Dist: pyproject-fmt==2.5.0; extra == "dev"
Requires-Dist: pyright==1.1.391; extra == "dev"
Requires-Dist: pyroma==4.2; extra == "dev"
Requires-Dist: pytest==8.3.4; extra == "dev"
Requires-Dist: pytest-cov==6.0.0; extra == "dev"
Requires-Dist: requests==2.32.3; extra == "dev"
Requires-Dist: ruff==0.9.1; extra == "dev"
Requires-Dist: shellcheck-py==0.10.0.1; extra == "dev"
Requires-Dist: shfmt-py==3.7.0.1; extra == "dev"
Requires-Dist: sphinx==8.1.3; extra == "dev"
Requires-Dist: sphinx-copybutton==0.5.2; extra == "dev"
Requires-Dist: sphinx-lint==1.0.0; extra == "dev"
Requires-Dist: sphinx-substitution-extensions==2025.1.2; extra == "dev"
Requires-Dist: sphinxcontrib-spelling==8.0.1; extra == "dev"
Requires-Dist: sybil==9.0.0; extra == "dev"
Requires-Dist: sybil-extras==2025.1.11; extra == "dev"
Requires-Dist: types-requests==2.32.0.20241016; extra == "dev"
Requires-Dist: vulture==2.14; extra == "dev"
Requires-Dist: yamlfix==1.17.0; extra == "dev"
Provides-Extra: release
Requires-Dist: check-wheel-contents==0.6.1; extra == "release"
